[{"Opponent":"Chennai Super Kings","Runs_Scored":"0","Balls_Played":"1","fours":"0","sixs":"0","Strike_Rate":"0.00","Match_No":"21st Match (N)","Match_Venue":"Abu Dhabi","Match_Date":"Oct 7 2020","Winning_Team":"Kolkata Knight Riders"},{"Opponent":"Delhi Capitals","Runs_Scored":"1","Balls_Played":"3","fours":"0","sixs":"0","Strike_Rate":"33.33","Match_No":"16th Match (N)","Match_Venue":"Sharjah","Match_Date":"Oct 3 2020","Winning_Team":"Delhi Capitals"},{"Opponent":"Mumbai Indians","Runs_Scored":"9","Balls_Played":"10","fours":"1","sixs":"0","Strike_Rate":"90.00","Match_No":"5th Match (N)","Match_Venue":"Abu Dhabi","Match_Date":"Sep 23 2020","Winning_Team":"Mumbai Indians"}]